_pygeoapi_process/nldi_flowtrace.py
_pygeoapi_process/nldi_splitcatchment.py
nldi_flowtools/__init__.py
nldi_flowtools/__main__.py
nldi_flowtools/flowtrace.py
nldi_flowtools/nldi_flowtools.py
nldi_flowtools/splitcatchment.py
nldi_flowtools/utils.py
nldi_flowtools-0.3.5.dist-info/LICENSE.md
nldi_flowtools-0.3.5.dist-info/METADATA
nldi_flowtools-0.3.5.dist-info/WHEEL
nldi_flowtools-0.3.5.dist-info/entry_points.txt
nldi_flowtools-0.3.5.dist-info/RECORD
