Metadata-Version: 2.3
Name: nldi-flowtools
Version: 0.3.5
Summary: NLDI Flowtools
License: LICENSE.md
Author: Anders Hopkins
Author-email: ahopkins@usgs.gov
Requires-Python: >=3.10,<3.14
Classifier: Development Status :: 4 - Beta
Classifier: License :: Other/Proprietary License
Classifier: Programming Language :: Python :: 3
Classifier: Programming Language :: Python :: 3.10
Classifier: Programming Language :: Python :: 3.11
Classifier: Programming Language :: Python :: 3.12
Classifier: Programming Language :: Python :: 3.13
Requires-Dist: Shapely (>=2,<3)
Requires-Dist: click (>=8.0,<9.0)
Requires-Dist: geojson (>=2.5.0,<3.0.0)
Requires-Dist: numpy (>=2.0.0)
Requires-Dist: pyflwdir (>=0.5,<0.6)
Requires-Dist: pyproj (>=3,<4)
Requires-Dist: rasterio (>=1.3.4,<2.0.0)
Requires-Dist: requests (>=2.26.0,<3.0.0)
Project-URL: Changelog, https://code.usgs.gov/wma/nhgf/toolsteam/nldi-flowtools/-/releases
Project-URL: Documentation, https://nldi-flowtools.readthedocs.io
Project-URL: Homepage, https://code.usgs.gov/wma/nhgf/toolsteam/nldi-flowtools
Project-URL: Repository, https://code.usgs.gov/wma/nhgf/toolsteam/nldi-flowtools
